{
  "project": {
    "name": "LedControlECU_TODO",
    "cycle_ms": 100
  },
  "dio": {
    "channels": [
      {
        "name": "DIO_CH_LED1",
        "id": 0,
        "port": "PTD",
        "pin": 15,
        "direction": "out",
        "active_high": true,
        "hint": "LED가 active-low 보드라면 active_high를 false로 바꾸고 generated/include/EcuC_Cfg.h를 재생성하세요."
      }
    ]
  },
  "future_modules": {
    "button": {
      "name": "DIO_CH_BUTTON1",
      "id": 1,
      "port": "PTC",
      "pin": 12,
      "direction": "in",
      "active_high": false,
      "status": "planned"
    },
    "adc": {
      "name": "ADC_CH_POTENTIOMETER1",
      "id": 0,
      "status": "planned"
    }
  }
}
